tair/__init__.py
tair/client.py
tair/cluster.py
tair/commands.py
tair/exceptions.py
tair/pipeline.py
tair/tairbloom.py
tair/taircpc.py
tair/tairdoc.py
tair/tairgis.py
tair/tairhash.py
tair/tairroaring.py
tair/tairsearch.py
tair/tairstring.py
tair/tairts.py
tair/tairvector.py
tair/tairzset.py
tair/typing.py
tair/asyncio/__init__.py
tair/asyncio/client.py
tair/asyncio/cluster.py
tair/asyncio/pipeline.py
tair-1.3.7.dist-info/LICENSE
tair-1.3.7.dist-info/METADATA
tair-1.3.7.dist-info/WHEEL
tair-1.3.7.dist-info/top_level.txt
tair-1.3.7.dist-info/RECORD
